fc_zbb_bigdata.py
zbb_fc_bigdata-1.0.dist-info/METADATA
zbb_fc_bigdata-1.0.dist-info/WHEEL
zbb_fc_bigdata-1.0.dist-info/top_level.txt
zbb_fc_bigdata-1.0.dist-info/RECORD
