Metadata-Version: 2.1
Name: zbb-fc-bigdata
Version: 1.0
Summary: 大数据3
Home-page: UNKNOWN
Author: UNKNOWN
Author-email: 2712034633@qq.com
License: UNKNOWN
Platform: UNKNOWN
